trame/__init__.py
trame/modules/__init__.py
trame/modules/plotly.py
trame/widgets/__init__.py
trame/widgets/plotly.py
trame_plotly/LICENSE
trame_plotly/__init__.py
trame_plotly/module/__init__.py
trame_plotly/module/serve/trame-plotly.umd.js
trame_plotly/module/serve/trame-plotly.umd.js.map
trame_plotly/widgets/__init__.py
trame_plotly/widgets/plotly.py
trame_plotly-3.0.2.dist-info/LICENSE
trame_plotly-3.0.2.dist-info/METADATA
trame_plotly-3.0.2.dist-info/WHEEL
trame_plotly-3.0.2.dist-info/top_level.txt
trame_plotly-3.0.2.dist-info/RECORD
